setup.py
terminal_chat_robot.egg-info/PKG-INFO
terminal_chat_robot.egg-info/SOURCES.txt
terminal_chat_robot.egg-info/dependency_links.txt
terminal_chat_robot.egg-info/entry_points.txt
terminal_chat_robot.egg-info/requires.txt
terminal_chat_robot.egg-info/top_level.txt
terminalchatrobot/__init__.py
terminalchatrobot/colors.py
terminalchatrobot/infos.py
terminalchatrobot/main.py
terminalchatrobot/robot.py