Metadata-Version: 1.1
Name: terminal-chat-robot
Version: 0.1.3
Summary: It is a terminal robot which can chat with you.
Home-page: UNKNOWN
Author: xingbofeng
Author-email: 503908971@qq.com
License: MIT License
Keywords: terminal,chat,robot
Platform: any
Classifier: Development Status :: 3 - Alpha
Classifier: Intended Audience :: Developers
Classifier: Topic :: Software Development :: Libraries
Classifier: License :: OSI Approved :: MIT License
Classifier: Programming Language :: Python :: 2
Classifier: Programming Language :: Python :: 2.6
Classifier: Programming Language :: Python :: 2.7
Classifier: Programming Language :: Python :: 3.3
Classifier: Programming Language :: Python :: 3.4
Classifier: Programming Language :: Python :: 3.5
